MANIFEST.in
README.md
requirements.txt
setup.py
deepcrawl_graphql/__init__.py
deepcrawl_graphql/api.py
deepcrawl_graphql/deepcrawl_schema.graphql
deepcrawl_graphql/exceptions.py
deepcrawl_graphql/mutations.py
deepcrawl_graphql/query.py
deepcrawl_graphql.egg-info/PKG-INFO
deepcrawl_graphql.egg-info/SOURCES.txt
deepcrawl_graphql.egg-info/dependency_links.txt
deepcrawl_graphql.egg-info/requires.txt
deepcrawl_graphql.egg-info/top_level.txt
deepcrawl_graphql/accounts/__init__.py
deepcrawl_graphql/accounts/account.py
deepcrawl_graphql/accounts/fields.py
deepcrawl_graphql/accounts/mutations.py
deepcrawl_graphql/crawls/__init__.py
deepcrawl_graphql/crawls/crawl.py
deepcrawl_graphql/crawls/fields.py
deepcrawl_graphql/crawls/mutations.py
deepcrawl_graphql/me/__init__.py
deepcrawl_graphql/me/fields.py
deepcrawl_graphql/me/me.py
deepcrawl_graphql/projects/__init__.py
deepcrawl_graphql/projects/fields.py
deepcrawl_graphql/projects/mutations.py
deepcrawl_graphql/projects/project.py
deepcrawl_graphql/reports/__init__.py
deepcrawl_graphql/reports/fields.py
deepcrawl_graphql/reports/mutations.py
deepcrawl_graphql/reports/report.py
deepcrawl_graphql/reports/report_type.py
deepcrawl_graphql/shortcuts/__init__.py
deepcrawl_graphql/shortcuts/account_shortcuts.py
deepcrawl_graphql/shortcuts/crawl_shortcuts.py
tests/test_integration.py