Metadata-Version: 2.1
Name: deepcrawl-graphql
Version: 0.2.13
Summary: A package to simplify usage of the DeepCrawl GraphQL
Home-page: https://github.com/DeepCrawlSEO/dc_graphql_wrapper
Author: Andrei Mutu
Author-email: mutuandrei02@gmail.com
Classifier: Programming Language :: Python :: 3
Classifier: License :: OSI Approved :: MIT License
Classifier: Operating System :: OS Independent
Requires-Python: >=3.7
Requires-Dist: gql[requests]==3.4.1
